hybrid_edge/__init__.py
hybrid_edge/client.py
hybrid_edge/proxy.py
hybrid_edge/sdk.py
hybrid_edge/server.py
hybrid_edge/utils.py
hybrid_edge-0.1.1.dist-info/licenses/LICENSE
hybrid_edge-0.1.1.dist-info/METADATA
hybrid_edge-0.1.1.dist-info/WHEEL
hybrid_edge-0.1.1.dist-info/entry_points.txt
hybrid_edge-0.1.1.dist-info/top_level.txt
hybrid_edge-0.1.1.dist-info/RECORD
