Metadata-Version: 2.4
Name: hybrid_edge
Version: 0.1.1
Summary: Secure Hybrid Edge-to-Cloud AI Tunneling
Requires-Python: >=3.8
License-File: LICENSE
Requires-Dist: requests
Requires-Dist: flask
Requires-Dist: python-dotenv
Dynamic: license-file
